deepcsim/__init__.py
deepcsim/cli.py
deepcsim/constants.py
deepcsim/py.typed
deepcsim/api/__init__.py
deepcsim/api/responses.py
deepcsim/api/server.py
deepcsim/api/routers/__init__.py
deepcsim/api/routers/analysis.py
deepcsim/api/routers/explorer.py
deepcsim/api/routers/files.py
deepcsim/api/schemas/__init__.py
deepcsim/api/schemas/analysis.py
deepcsim/api/schemas/file.py
deepcsim/api/schemas/scan.py
deepcsim/api/static/css/default.min.css
deepcsim/api/static/js/highlight.min.js
deepcsim/api/templates/explorer.html
deepcsim/api/templates/index.html
deepcsim/core/__init__.py
deepcsim/core/analyzer.py
deepcsim/core/comparator.py
deepcsim/core/metrics.py
deepcsim/core/scanner.py
deepcsim/core/similarity.py
deepcsim/utils/file_info.py
deepcsim-0.1.2.dist-info/licenses/LICENSE
deepcsim-0.1.2.dist-info/METADATA
deepcsim-0.1.2.dist-info/WHEEL
deepcsim-0.1.2.dist-info/entry_points.txt
deepcsim-0.1.2.dist-info/top_level.txt
deepcsim-0.1.2.dist-info/RECORD
