Metadata-Version: 2.4
Name: deepcsim
Version: 0.1.2
Summary: A code similarity analyzer using AST analysis.
Author-email: Wahib Mzali <mzaliwahib04@gmail.com>
Project-URL: Homepage, https://github.com/whm04/deepcsim
Project-URL: Bug Tracker, https://github.com/whm04/deepcsim/issues
Classifier: Programming Language :: Python :: 3
Classifier: License :: OSI Approved :: MIT License
Classifier: Operating System :: OS Independent
Requires-Python: <3.14,>=3.11
License-File: LICENSE
Requires-Dist: fastapi
Requires-Dist: uvicorn
Requires-Dist: python-multipart
Requires-Dist: jinja2
Provides-Extra: test
Requires-Dist: pytest; extra == "test"
Requires-Dist: pytest-cov; extra == "test"
Dynamic: license-file
